assignment3/player.v
module PLayer(
    input [63:0] in_data,
    output wire [63:0] out_data
);
    wire [63:0]in = in_data;
    assign out_data[0] = in[0];
    assign out_data[16] = in[1];
    assign out_data[32] = in[2];
    assign out_data[48] = in[3];
    assign out_data[1] = in[4];
    assign out_data[17] = in[5];
    assign out_data[33] = in[6];
    assign out_data[49] = in[7];
    assign out_data[2] = in[8];
    assign out_data[18] = in[9];
    assign out_data[34] = in[10];
    assign out_data[50] = in[11];
    assign out_data[3] = in[12];
    assign out_data[19] = in[13];
    assign out_data[35] = in[14];
    assign out_data[51] = in[15];
    assign out_data[4] = in[16];
    assign out_data[20] = in[17];
    assign out_data[36] = in[18];
    assign out_data[52] = in[19];
    assign out_data[5] = in[20];
    assign out_data[21] = in[21];
    assign out_data[37] = in[22];
    assign out_data[53] = in[23];
    assign out_data[6] = in[24];
    assign out_data[22] = in[25];
    assign out_data[38] = in[26];
    assign out_data[54] = in[27];
    assign out_data[7] = in[28];
    assign out_data[23] = in[29];
    assign out_data[39] = in[30];
    assign out_data[55] = in[31];
    assign out_data[8] = in[32];
    assign out_data[24] = in[33];
    assign out_data[40] = in[34];
    assign out_data[56] = in[35];
    assign out_data[9] = in[36];
    assign out_data[25] = in[37];
    assign out_data[41] = in[38];
    assign out_data[57] = in[39];
    assign out_data[10] = in[40];
    assign out_data[26] = in[41];
    assign out_data[42] = in[42];
    assign out_data[58] = in[43];
    assign out_data[11] = in[44];
    assign out_data[27] = in[45];
    assign out_data[43] = in[46];
    assign out_data[59] = in[47];
    assign out_data[12] = in[48];
    assign out_data[28] = in[49];
    assign out_data[44] = in[50];
    assign out_data[60] = in[51];
    assign out_data[13] = in[52];
    assign out_data[29] = in[53];
    assign out_data[45] = in[54];
    assign out_data[61] = in[55];
    assign out_data[14] = in[56];
    assign out_data[30] = in[57];
    assign out_data[46] = in[58];
    assign out_data[62] = in[59];
    assign out_data[15] = in[60];
    assign out_data[31] = in[61];
    assign out_data[47] = in[62];
    assign out_data[63] = in[63];

endmodule

assignment3/tb_player.v
`timescale 1ns/1ps

module tb_player();
    wire [63:0] out;
    wire [63:0] in = 64'hcccccccccccccccc;
    PLayer p (in, out);
    integer i;

    reg clk;
    initial begin
        forever #4 clk = ~clk;
    end

    initial begin
        i = 0;
        clk = 0;
    end

    always @ * begin
        if (i == 72) begin
            $finish();
        end
    end

    always @ (posedge clk) begin
        i <= i + 1;
    end

    initial begin
        $dumpfile("player.vcd");
        $dumpvars(0, tb_player);
    end
endmodule

assignment3/player.vcd
$date
	Tue Mar 12 22:44:36 2024
$end
$version
	Icarus Verilog
$end
$timescale
	1ps
$end
$scope module tb_player $end
$var wire 64 ! in [63:0] $end
$var wire 64 " out [63:0] $end
$var reg 1 # clk $end
$var integer 32 $ i [31:0] $end
$scope module p $end
$var wire 64 % in [63:0] $end
$var wire 64 & in_data [63:0] $end
$var wire 64 ' out_data [63:0] $end
$upscope $end
$upscope $end
$enddefinitions $end
$comment Show the parameter values. $end
$dumpall
$end
#0
$dumpvars
b1111111111111111111111111111111100000000000000000000000000000000 '
b1100110011001100110011001100110011001100110011001100110011001100 &
b1100110011001100110011001100110011001100110011001100110011001100 %
b0 $
0#
b1111111111111111111111111111111100000000000000000000000000000000 "
b1100110011001100110011001100110011001100110011001100110011001100 !
$end
#4000
b1 $
1#
#8000
0#
#12000
b10 $
1#
#16000
0#
#20000
b11 $
1#
#24000
0#
#28000
b100 $
1#
#32000
0#
#36000
b101 $
1#
#40000
0#
#44000
b110 $
1#
#48000
0#
#52000
b111 $
1#
#56000
0#
#60000
b1000 $
1#
#64000
0#
#68000
b1001 $
1#
#72000
0#
#76000
b1010 $
1#
#80000
0#
#84000
b1011 $
1#
#88000
0#
#92000
b1100 $
1#
#96000
0#
#100000
b1101 $
1#
#104000
0#
#108000
b1110 $
1#
#112000
0#
#116000
b1111 $
1#
#120000
0#
#124000
b10000 $
1#
#128000
0#
#132000
b10001 $
1#
#136000
0#
#140000
b10010 $
1#
#144000
0#
#148000
b10011 $
1#
#152000
0#
#156000
b10100 $
1#
#160000
0#
#164000
b10101 $
1#
#168000
0#
#172000
b10110 $
1#
#176000
0#
#180000
b10111 $
1#
#184000
0#
#188000
b11000 $
1#
#192000
0#
#196000
b11001 $
1#
#200000
0#
#204000
b11010 $
1#
#208000
0#
#212000
b11011 $
1#
#216000
0#
#220000
b11100 $
1#
#224000
0#
#228000
b11101 $
1#
#232000
0#
#236000
b11110 $
1#
#240000
0#
#244000
b11111 $
1#
#248000
0#
#252000
b100000 $
1#
#256000
0#
#260000
b100001 $
1#
#264000
0#
#268000
b100010 $
1#
#272000
0#
#276000
b100011 $
1#
#280000
0#
#284000
b100100 $
1#
#288000
0#
#292000
b100101 $
1#
#296000
0#
#300000
b100110 $
1#
#304000
0#
#308000
b100111 $
1#
#312000
0#
#316000
b101000 $
1#
#320000
0#
#324000
b101001 $
1#
#328000
0#
#332000
b101010 $
1#
#336000
0#
#340000
b101011 $
1#
#344000
0#
#348000
b101100 $
1#
#352000
0#
#356000
b101101 $
1#
#360000
0#
#364000
b101110 $
1#
#368000
0#
#372000
b101111 $
1#
#376000
0#
#380000
b110000 $
1#
#384000
0#
#388000
b110001 $
1#
#392000
0#
#396000
b110010 $
1#
#400000
0#
#404000
b110011 $
1#
#408000
0#
#412000
b110100 $
1#
#416000
0#
#420000
b110101 $
1#
#424000
0#
#428000
b110110 $
1#
#432000
0#
#436000
b110111 $
1#
#440000
0#
#444000
b111000 $
1#
#448000
0#
#452000
b111001 $
1#
#456000
0#
#460000
b111010 $
1#
#464000
0#
#468000
b111011 $
1#
#472000
0#
#476000
b111100 $
1#
#480000
0#
#484000
b111101 $
1#
#488000
0#
#492000
b111110 $
1#
#496000
0#
#500000
b111111 $
1#
#504000
0#
#508000
b1000000 $
1#
#512000
0#
#516000
b1000001 $
1#
#520000
0#
#524000
b1000010 $
1#
#528000
0#
#532000
b1000011 $
1#
#536000
0#
#540000
b1000100 $
1#
#544000
0#
#548000
b1000101 $
1#
#552000
0#
#556000
b1000110 $
1#
#560000
0#
#564000
b1000111 $
1#
#568000
0#
#572000
b1001000 $
1#
