assignment3/player.v
module PLayer(
    input [63:0] in_data,
    output wire [63:0] out_data
);
    wire [63:0]in = in_data;
    assign out_data[0] = in[0];
    assign out_data[16] = in[1];
    assign out_data[32] = in[2];
    assign out_data[48] = in[3];
    assign out_data[1] = in[4];
    assign out_data[17] = in[5];
    assign out_data[33] = in[6];
    assign out_data[49] = in[7];
    assign out_data[2] = in[8];
    assign out_data[18] = in[9];
    assign out_data[34] = in[10];
    assign out_data[50] = in[11];
    assign out_data[3] = in[12];
    assign out_data[19] = in[13];
    assign out_data[35] = in[14];
    assign out_data[51] = in[15];
    assign out_data[4] = in[16];
    assign out_data[20] = in[17];
    assign out_data[36] = in[18];
    assign out_data[52] = in[19];
    assign out_data[5] = in[20];
    assign out_data[21] = in[21];
    assign out_data[37] = in[22];
    assign out_data[53] = in[23];
    assign out_data[6] = in[24];
    assign out_data[22] = in[25];
    assign out_data[38] = in[26];
    assign out_data[54] = in[27];
    assign out_data[7] = in[28];
    assign out_data[23] = in[29];
    assign out_data[39] = in[30];
    assign out_data[55] = in[31];
    assign out_data[8] = in[32];
    assign out_data[24] = in[33];
    assign out_data[40] = in[34];
    assign out_data[56] = in[35];
    assign out_data[9] = in[36];
    assign out_data[25] = in[37];
    assign out_data[41] = in[38];
    assign out_data[57] = in[39];
    assign out_data[10] = in[40];
    assign out_data[26] = in[41];
    assign out_data[42] = in[42];
    assign out_data[58] = in[43];
    assign out_data[11] = in[44];
    assign out_data[27] = in[45];
    assign out_data[43] = in[46];
    assign out_data[59] = in[47];
    assign out_data[12] = in[48];
    assign out_data[28] = in[49];
    assign out_data[44] = in[50];
    assign out_data[60] = in[51];
    assign out_data[13] = in[52];
    assign out_data[29] = in[53];
    assign out_data[45] = in[54];
    assign out_data[61] = in[55];
    assign out_data[14] = in[56];
    assign out_data[30] = in[57];
    assign out_data[46] = in[58];
    assign out_data[62] = in[59];
    assign out_data[15] = in[60];
    assign out_data[31] = in[61];
    assign out_data[47] = in[62];
    assign out_data[63] = in[63];

endmodule

assignment3/sbox_table.v
module sbox_table(
    input wire [3:0] in,
    output reg [3:0] out
);
    always @(*) begin
        case (in)
            4'h0 : out = 4'hC;
            4'h1 : out = 4'h5; 
            4'h2 : out = 4'h6;
            4'h3 : out = 4'hB;
            4'h4 : out = 4'h9;
            4'h5 : out = 4'h0;
            4'h6 : out = 4'hA;
            4'h7 : out = 4'hD;
            4'h8 : out = 4'h3;
            4'h9 : out = 4'hE;
            4'hA : out = 4'hF;
            4'hB : out = 4'h8;
            4'hC : out = 4'h4;
            4'hD : out = 4'h7;
            4'hE : out = 4'h1;
            4'hF : out = 4'h2;
        endcase
    end
endmodule

assignment3/sboxlayer.v
module SboxLayer(
    input [63:0] state,
    output [63:0] result
);
    genvar i;
    generate
        for (i = 0; i < 16; i = i + 1) begin : sbox_gen
            wire [3:0] in = state[4*i +: 4];
            wire [3:0] out;
            sbox_table st (.in(in), .out(out));
            assign result[4*i +: 4] = out;
        end
    endgenerate
endmodule

assignment3/encryptor.v
module encryptor(
    input [63:0] round_key,
    input [63:0] state,
    output [63:0] result
);

wire [63:0] addroundkey;
wire [63:0] sbox;

assign addroundkey = round_key ^ state;

SboxLayer sbox_ins( 
    .state(addroundkey), 
    .result(sbox) 
);

PLayer player_ins( 
    .in_data(sbox), 
    .out_data(result) 
);

endmodule

assignment3/key_scheduler.v
module key_scheduler(
    input clk,
    input enb,
    input load,
    input [79:0] key_in,
    input[4:0] count,
    output reg [63:0] key_out
);

    reg [79:0] round_key;
    reg [79:0] key_modified;
    reg [3:0] sbox_in;
    reg [3:0] sbox_out;

    always @(negedge clk or posedge load) begin
        if (load) begin
            round_key = key_in;  
        end else if (enb) begin
            key_out = round_key[79:16];

            round_key = { round_key[18:0], round_key[79:19] };
            sbox_in = round_key[79:76];

            key_modified[79:20] = round_key[79:20];
            key_modified[19:15] = round_key[19:15] ^ count;
            key_modified[14:0] = round_key[14:0];

            case (sbox_in)
                4'h0 : sbox_out = 4'hC;
                4'h1 : sbox_out = 4'h5; 
                4'h2 : sbox_out = 4'h6;
                4'h3 : sbox_out = 4'hB;
                4'h4 : sbox_out = 4'h9;
                4'h5 : sbox_out = 4'h0;
                4'h6 : sbox_out = 4'hA;
                4'h7 : sbox_out = 4'hD;
                4'h8 : sbox_out = 4'h3;
                4'h9 : sbox_out = 4'hE;
                4'hA : sbox_out = 4'hF;
                4'hB : sbox_out = 4'h8;
                4'hC : sbox_out = 4'h4;
                4'hD : sbox_out = 4'h7;
                4'hE : sbox_out = 4'h1;
                4'hF : sbox_out = 4'h2;
            endcase

            round_key = {sbox_out, key_modified[75:0]};
        end
    end

endmodule

assignment3/enc.v
module enc(
    input clk,
    input rst_n,
    input start_enc,
    input [79:0] key,
    input [63:0] plaintext,

    output wire ready,
    output [63:0] cipher_text
);
    reg [4:0] count;
    wire [63:0] round_key;
    reg [63:0] state;
    wire [63:0] round_result;
    reg [63:0] final_result;
    reg load, enb;
    reg tick;

    // key_scheduler will run on the negative edge to sync the signals.
    key_scheduler ksc(
        .clk(clk),
        .enb(enb),
        .load(load),
        .key_in(key),
        .count(count),
        .key_out(round_key)
    );

    // The round_key will drives this encryptor module.
    encryptor encrypt(
        .round_key(round_key),
        .state(state),
        .result(round_result)
    );

    localparam INIT = 0, START = 1, EXECUTE = 2, FIN = 3, rounds = 31;

    reg [1:0] curr_state, next_state;

    always @(*) begin
        next_state = curr_state;

        case (curr_state)
            INIT : if (start_enc) begin
                load = 1'b1;    
                state = plaintext;
                next_state = START;
            end
            START : begin
                count = 5'b1;
                enb = 1'b1;
                load = 1'b0;
                next_state = EXECUTE;
            end
            EXECUTE : begin
                if (count == 0) begin
                    final_result = state;
                    next_state = FIN;
                end
            end
            FIN : begin
                final_result = final_result ^ round_key;
                enb = 1'b0;
                load = 1'b1;
                next_state = INIT;
            end
        endcase
    end

    always @(posedge clk) begin
        if (curr_state == EXECUTE) begin
            state = round_result; // This will collect the result from last round.
            count = count + 5'b1;
        end
    end

    always @(posedge clk or posedge rst_n) begin
        if (!rst_n) begin
            enb = 1'b0;
            load = 1'b0;
            count = 5'b0;
            curr_state = INIT;
        end else begin
            curr_state = next_state;
        end
    end

    assign ready = (curr_state == FIN) ? 1'b1 : 1'b0;
    assign cipher_text = final_result;

endmodule

assignment3/tb_keyscheduler.v
`timescale 1ns/1ps

module tb_enc();

reg clk, rst_n;
reg start, stop, load, enb, start_enc;
wire ready;
integer i;
wire [5:0] count;
wire [63:0] round_key;
reg [63:0] plain_text;
wire [63:0] cipher_text;
reg [79:0] user_key;

initial begin
    clk = 1'b0;
    user_key = 80'b0;
    plain_text = 64'b0;
    forever #4 clk = ~clk;
end

initial begin
    rst_n = 1'b0;
    #8;
    rst_n = 1'b1;
end

initial begin
    i = 0;
end

enc enc1(
    .clk(clk),
    .rst_n(rst_n),
    .start_enc(start_enc),
    .key(user_key),
    .plaintext(plain_text),
    .ready(ready),
    .cipher_text(cipher_text)
);

always @ * begin
    if (i == 4) begin
        start_enc = 1'b1;
    end
    if (i == 72) begin
        $finish();
    end
end

always @ (posedge clk) begin
    if (rst_n) begin
        i <= i + 1;
    end
end

initial begin
    $dumpfile("scheduler.vcd");
    $dumpvars(0, tb_enc);
end

endmodule

assignment3/scheduler.vcd
$date
	Tue Mar 12 23:35:35 2024
$end
$version
	Icarus Verilog
$end
$timescale
	1ps
$end
$scope module tb_enc $end
$var wire 1 ! ready $end
$var wire 64 " cipher_text [63:0] $end
$var reg 1 # clk $end
$var reg 64 $ plain_text [63:0] $end
$var reg 1 % rst_n $end
$var reg 1 & start_enc $end
$var reg 80 ' user_key [79:0] $end
$var integer 32 ( i [31:0] $end
$scope module enc1 $end
$var wire 64 ) cipher_text [63:0] $end
$var wire 1 # clk $end
$var wire 80 * key [79:0] $end
$var wire 64 + plaintext [63:0] $end
$var wire 1 % rst_n $end
$var wire 1 & start_enc $end
$var wire 64 , round_result [63:0] $end
$var wire 64 - round_key [63:0] $end
$var wire 1 ! ready $end
$var parameter 32 . EXECUTE $end
$var parameter 32 / FIN $end
$var parameter 32 0 INIT $end
$var parameter 32 1 START $end
$var parameter 32 2 rounds $end
$var reg 5 3 count [4:0] $end
$var reg 2 4 curr_state [1:0] $end
$var reg 1 5 enb $end
$var reg 64 6 final_result [63:0] $end
$var reg 1 7 load $end
$var reg 2 8 next_state [1:0] $end
$var reg 64 9 state [63:0] $end
$scope module encrypt $end
$var wire 64 : addroundkey [63:0] $end
$var wire 64 ; state [63:0] $end
$var wire 64 < sbox [63:0] $end
$var wire 64 = round_key [63:0] $end
$var wire 64 > result [63:0] $end
$scope module player_ins $end
$var wire 64 ? in [63:0] $end
$var wire 64 @ out_data [63:0] $end
$var wire 64 A in_data [63:0] $end
$upscope $end
$scope module sbox_ins $end
$var wire 64 B state [63:0] $end
$var wire 64 C result [63:0] $end
$scope begin sbox_gen[0] $end
$var wire 4 D in [3:0] $end
$var wire 4 E out [3:0] $end
$var parameter 2 F i $end
$scope module st $end
$var wire 4 G in [3:0] $end
$var reg 4 H out [3:0] $end
$upscope $end
$upscope $end
$scope begin sbox_gen[1] $end
$var wire 4 I in [3:0] $end
$var wire 4 J out [3:0] $end
$var parameter 2 K i $end
$scope module st $end
$var wire 4 L in [3:0] $end
$var reg 4 M out [3:0] $end
$upscope $end
$upscope $end
$scope begin sbox_gen[2] $end
$var wire 4 N in [3:0] $end
$var wire 4 O out [3:0] $end
$var parameter 3 P i $end
$scope module st $end
$var wire 4 Q in [3:0] $end
$var reg 4 R out [3:0] $end
$upscope $end
$upscope $end
$scope begin sbox_gen[3] $end
$var wire 4 S in [3:0] $end
$var wire 4 T out [3:0] $end
$var parameter 3 U i $end
$scope module st $end
$var wire 4 V in [3:0] $end
$var reg 4 W out [3:0] $end
$upscope $end
$upscope $end
$scope begin sbox_gen[4] $end
$var wire 4 X in [3:0] $end
$var wire 4 Y out [3:0] $end
$var parameter 4 Z i $end
$scope module st $end
$var wire 4 [ in [3:0] $end
$var reg 4 \ out [3:0] $end
$upscope $end
$upscope $end
$scope begin sbox_gen[5] $end
$var wire 4 ] in [3:0] $end
$var wire 4 ^ out [3:0] $end
$var parameter 4 _ i $end
$scope module st $end
$var wire 4 ` in [3:0] $end
$var reg 4 a out [3:0] $end
$upscope $end
$upscope $end
$scope begin sbox_gen[6] $end
$var wire 4 b in [3:0] $end
$var wire 4 c out [3:0] $end
$var parameter 4 d i $end
$scope module st $end
$var wire 4 e in [3:0] $end
$var reg 4 f out [3:0] $end
$upscope $end
$upscope $end
$scope begin sbox_gen[7] $end
$var wire 4 g in [3:0] $end
$var wire 4 h out [3:0] $end
$var parameter 4 i i $end
$scope module st $end
$var wire 4 j in [3:0] $end
$var reg 4 k out [3:0] $end
$upscope $end
$upscope $end
$scope begin sbox_gen[8] $end
$var wire 4 l in [3:0] $end
$var wire 4 m out [3:0] $end
$var parameter 5 n i $end
$scope module st $end
$var wire 4 o in [3:0] $end
$var reg 4 p out [3:0] $end
$upscope $end
$upscope $end
$scope begin sbox_gen[9] $end
$var wire 4 q in [3:0] $end
$var wire 4 r out [3:0] $end
$var parameter 5 s i $end
$scope module st $end
$var wire 4 t in [3:0] $end
$var reg 4 u out [3:0] $end
$upscope $end
$upscope $end
$scope begin sbox_gen[10] $end
$var wire 4 v in [3:0] $end
$var wire 4 w out [3:0] $end
$var parameter 5 x i $end
$scope module st $end
$var wire 4 y in [3:0] $end
$var reg 4 z out [3:0] $end
$upscope $end
$upscope $end
$scope begin sbox_gen[11] $end
$var wire 4 { in [3:0] $end
$var wire 4 | out [3:0] $end
$var parameter 5 } i $end
$scope module st $end
$var wire 4 ~ in [3:0] $end
$var reg 4 !" out [3:0] $end
$upscope $end
$upscope $end
$scope begin sbox_gen[12] $end
$var wire 4 "" in [3:0] $end
$var wire 4 #" out [3:0] $end
$var parameter 5 $" i $end
$scope module st $end
$var wire 4 %" in [3:0] $end
$var reg 4 &" out [3:0] $end
$upscope $end
$upscope $end
$scope begin sbox_gen[13] $end
$var wire 4 '" in [3:0] $end
$var wire 4 (" out [3:0] $end
$var parameter 5 )" i $end
$scope module st $end
$var wire 4 *" in [3:0] $end
$var reg 4 +" out [3:0] $end
$upscope $end
$upscope $end
$scope begin sbox_gen[14] $end
$var wire 4 ," in [3:0] $end
$var wire 4 -" out [3:0] $end
$var parameter 5 ." i $end
$scope module st $end
$var wire 4 /" in [3:0] $end
$var reg 4 0" out [3:0] $end
$upscope $end
$upscope $end
$scope begin sbox_gen[15] $end
$var wire 4 1" in [3:0] $end
$var wire 4 2" out [3:0] $end
$var parameter 5 3" i $end
$scope module st $end
$var wire 4 4" in [3:0] $end
$var reg 4 5" out [3:0] $end
$upscope $end
$upscope $end
$upscope $end
$upscope $end
$scope module ksc $end
$var wire 1 # clk $end
$var wire 5 6" count [4:0] $end
$var wire 1 5 enb $end
$var wire 80 7" key_in [79:0] $end
$var wire 1 7 load $end
$var reg 80 8" key_modified [79:0] $end
$var reg 64 9" key_out [63:0] $end
$var reg 80 :" round_key [79:0] $end
$var reg 4 ;" sbox_in [3:0] $end
$var reg 4 <" sbox_out [3:0] $end
$upscope $end
$upscope $end
$upscope $end
$enddefinitions $end
$comment Show the parameter values. $end
$dumpall
b1111 3"
b1110 ."
b1101 )"
b1100 $"
b1011 }
b1010 x
b1001 s
b1000 n
b111 i
b110 d
b101 _
b100 Z
b11 U
b10 P
b1 K
b0 F
b11111 2
b1 1
b0 0
b11 /
b10 .
$end
#0
$dumpvars
bx <"
bx ;"
bx :"
bx 9"
bx 8"
b0 7"
bx 6"
bx 5"
bx 4"
bx 2"
bx 1"
bx 0"
bx /"
bx -"
bx ,"
bx +"
bx *"
bx ("
bx '"
bx &"
bx %"
bx #"
bx ""
bx !"
bx ~
bx |
bx {
bx z
bx y
bx w
bx v
bx u
bx t
bx r
bx q
bx p
bx o
bx m
bx l
bx k
bx j
bx h
bx g
bx f
bx e
bx c
bx b
bx a
bx `
bx ^
bx ]
bx \
bx [
bx Y
bx X
bx W
bx V
bx T
bx S
bx R
bx Q
bx O
bx N
bx M
bx L
bx J
bx I
bx H
bx G
bx E
bx D
bx C
bx B
bx A
bx @
bx ?
bx >
bx =
bx <
bx ;
bx :
bx 9
bx 8
x7
bx 6
x5
bx 4
bx 3
bx -
bx ,
b0 +
b0 *
bx )
b0 (
b0 '
x&
0%
b0 $
0#
bx "
x!
$end
#4000
0!
b0 8
b0 4
b0 3
b0 6"
07
05
1#
#8000
0#
1%
#12000
b1 (
1#
#16000
0#
#20000
b10 (
1#
#24000
0#
#28000
b11 (
1#
#32000
0#
#36000
b0 :"
b1 8
b0 9
b0 ;
17
1&
b100 (
1#
#40000
0#
#44000
b101 (
b10 8
07
15
b1 3
b1 6"
b1 4
1#
#48000
b1111111111111111111111111111111100000000000000000000000000000000 ,
b1111111111111111111111111111111100000000000000000000000000000000 >
b1111111111111111111111111111111100000000000000000000000000000000 @
b1100 E
b1100 H
b1100 J
b1100 M
b1100 O
b1100 R
b1100 T
b1100 W
b1100 Y
b1100 \
b1100 ^
b1100 a
b1100 c
b1100 f
b1100 h
b1100 k
b1100 m
b1100 p
b1100 r
b1100 u
b1100 w
b1100 z
b1100 |
b1100 !"
b1100 #"
b1100 &"
b1100 ("
b1100 +"
b1100 -"
b1100 0"
b1100110011001100110011001100110011001100110011001100110011001100 ?
b1100110011001100110011001100110011001100110011001100110011001100 <
b1100110011001100110011001100110011001100110011001100110011001100 A
b1100110011001100110011001100110011001100110011001100110011001100 C
b1100 2"
b1100 5"
b0 D
b0 G
b0 I
b0 L
b0 N
b0 Q
b0 S
b0 V
b0 X
b0 [
b0 ]
b0 `
b0 b
b0 e
b0 g
b0 j
b0 l
b0 o
b0 q
b0 t
b0 v
b0 y
b0 {
b0 ~
b0 ""
b0 %"
b0 '"
b0 *"
b0 ,"
b0 /"
b0 1"
b0 4"
b0 :
b0 B
b10 8
b11000000000000000000000000000000000000000000000000000000000000001000000000000000 :"
b1100 <"
b1000000000000000 8"
b0 ;"
b0 -
b0 =
b0 9"
0#
#52000
b110 (
b11111111000000001111111111111111000000000000000000000000 ,
b11111111000000001111111111111111000000000000000000000000 >
b11111111000000001111111111111111000000000000000000000000 @
b10 m
b10 p
b10 r
b10 u
b10 w
b10 z
b10 |
b10 !"
b10 #"
b10 &"
b10 ("
b10 +"
b10 -"
b10 0"
b10001000100010001000100010001011001100110011001100110011001100 ?
b10001000100010001000100010001011001100110011001100110011001100 <
b10001000100010001000100010001011001100110011001100110011001100 A
b10001000100010001000100010001011001100110011001100110011001100 C
b10 2"
b10 5"
b1111 l
b1111 o
b1111 q
b1111 t
b1111 v
b1111 y
b1111 {
b1111 ~
b1111 ""
b1111 %"
b1111 '"
b1111 *"
b1111 ,"
b1111 /"
b1111 1"
b1111 4"
b1111111111111111111111111111111100000000000000000000000000000000 :
b1111111111111111111111111111111100000000000000000000000000000000 B
b10 3
b10 6"
b1111111111111111111111111111111100000000000000000000000000000000 9
b1111111111111111111111111111111100000000000000000000000000000000 ;
b10 4
1#
#56000
b1000000011111111000000001111111111111111000000001000000000000000 ,
b1000000011111111000000001111111111111111000000001000000000000000 >
b1000000011111111000000001111111111111111000000001000000000000000 @
b1011001000100010001000100010001011001100110011001100110011001100 ?
b1011001000100010001000100010001011001100110011001100110011001100 <
b1011001000100010001000100010001011001100110011001100110011001100 A
b1011001000100010001000100010001011001100110011001100110011001100 C
b1011 2"
b1011 5"
b11 1"
b11 4"
b11111111111111111111111111111100000000000000000000000000000000 :
b11111111111111111111111111111100000000000000000000000000000000 B
b101 <"
b10000000000000001100000000000000000000000000000000000000000010000000000000000 8"
b1 ;"
b1010000000000000001100000000000000000000000000000000000000000010000000000000000 :"
b1100000000000000000000000000000000000000000000000000000000000000 -
b1100000000000000000000000000000000000000000000000000000000000000 =
b1100000000000000000000000000000000000000000000000000000000000000 9"
0#
#60000
b111 (
b1100110000110111010011000011011100110011110010001000000000001000 ,
b1100110000110111010011000011011100110011110010001000000000001000 >
b1100110000110111010011000011011100110011110010001000000000001000 @
b11 T
b11 W
b10 c
b10 f
b10 h
b10 k
b1100 w
b1100 z
b1100 |
b1100 !"
b1100 -"
b1100 0"
b1001110000100010110011000010001000100010110011000011110011001100 ?
b1001110000100010110011000010001000100010110011000011110011001100 <
b1001110000100010110011000010001000100010110011000011110011001100 A
b1001110000100010110011000010001000100010110011000011110011001100 C
b1001 2"
b1001 5"
b1000 S
b1000 V
b1111 b
b1111 e
b1111 g
b1111 j
b0 v
b0 y
b0 {
b0 ~
b0 ,"
b0 /"
b100 1"
b100 4"
b100000011111111000000001111111111111111000000001000000000000000 :
b100000011111111000000001111111111111111000000001000000000000000 B
b11 3
b11 6"
b1000000011111111000000001111111111111111000000001000000000000000 9
b1000000011111111000000001111111111111111000000001000000000000000 ;
1#
#64000
b100000000110110110010000011011110110111110010001000110000001001 ,
b100000000110110110010000011011110110111110010001000110000001001 >
b100000000110110110010000011011110110111110010001000110000001001 @
b101 E
b101 H
b11 w
b11 z
b101 |
b101 !"
b111110000100010010100110010001000100010110011000011110011000101 ?
b111110000100010010100110010001000100010110011000011110011000101 <
b111110000100010010100110010001000100010110011000011110011000101 A
b111110000100010010100110010001000100010110011000011110011000101 C
b111 2"
b111 5"
b1 D
b1 G
b1000 v
b1000 y
b1 {
b1 ~
b1101 1"
b1101 4"
b1101000011111111000110001111111111111111000000001000000000000001 :
b1101000011111111000110001111111111111111000000001000000000000001 B
b110 <"
b100000000000000000101000000000000000110000000000000000000000011000000000000000 8"
b10 ;"
b1100000000000000000101000000000000000110000000000000000000000011000000000000000 :"
b101000000000000000110000000000000000000000000000000000000000001 -
b101000000000000000110000000000000000000000000000000000000000001 =
b101000000000000000110000000000000000000000000000000000000000001 9"
0#
#68000
b1000 (
b111011111000010110011010110011000111010000110011010101101011001 ,
b111011111000010110011010110011000111010000110011010101101011001 >
b111011111000010110011010110011000111010000110011010101101011001 @
b11 E
b11 H
b100 O
b100 R
b11 Y
b11 \
b100 ^
b100 a
b1101 c
b1101 f
b1000 h
b1000 k
b1101 m
b1101 p
b1011 r
b1011 u
b1100 w
b1100 z
b111 |
b111 !"
b1010 #"
b1010 &"
b1011 ("
b1011 +"
b101110010111010011111001011110110001101010000110011010011000011 ?
b101110010111010011111001011110110001101010000110011010011000011 <
b101110010111010011111001011110110001101010000110011010011000011 A
b101110010111010011111001011110110001101010000110011010011000011 C
b101 2"
b101 5"
b1000 D
b1000 G
b1100 N
b1100 Q
b1000 X
b1000 [
b1100 ]
b1100 `
b111 b
b111 e
b1011 g
b1011 j
b111 l
b111 o
b11 q
b11 t
b0 v
b0 y
b1101 {
b1101 ~
b110 ""
b110 %"
b11 '"
b11 *"
b1 1"
b1 4"
b1000000110110110100000011011110110111110010001000110000001000 :
b1000000110110110100000011011110110111110010001000110000001000 B
b100 3
b100 6"
b100000000110110110010000011011110110111110010001000110000001001 9
b100000000110110110010000011011110110111110010001000110000001001 ;
1#
#72000
b111001111000010110011010010011010110110000110010010001101011001 ,
b111001111000010110011010010011010110110000110010010001101011001 >
b111001111000010110011010010011010110110000110010010001101011001 @
b1001 c
b1001 f
b110 w
b110 z
b100 |
b100 !"
b110110010111010010001101011110110001001010000110011010011000011 ?
b110110010111010010001101011110110001001010000110011010011000011 <
b110110010111010010001101011110110001001010000110011010011000011 A
b110110010111010010001101011110110001001010000110011010011000011 C
b110 2"
b110 5"
b100 b
b100 e
b10 v
b10 y
b1100 {
b1100 ~
b10 1"
b10 4"
b10000000110110110000100011011110110100110010001000110000001000 :
b10000000110110110000100011011110110100110010001000110000001000 B
b1011 <"
b110000000000000000110000000000000000010100000000000000011000100000000000000000 8"
b11 ;"
b10110000000000000000110000000000000000010100000000000000011000100000000000000000 :"
b110000000000000000010100000000000000011000000000000000000000001 -
b110000000000000000010100000000000000011000000000000000000000001 =
b110000000000000000010100000000000000011000000000000000000000001 9"
0#
#76000
b1001 (
b100010110010100101111100011100001010011000111011100010000100101 ,
b100010110010100101111100011100001010011000111011100010000100101 >
b100010110010100101111100011100001010011000111011100010000100101 @
b0 J
b0 M
b1011 O
b1011 R
b110 T
b110 W
b1110 Y
b1110 \
b101 ^
b101 a
b0 c
b0 f
b1010 m
b1010 p
b110 r
b110 u
b1101 w
b1101 z
b110 #"
b110 &"
b100 ("
b100 +"
b1011 -"
b1011 0"
b101101101000110010011010110101010000000010111100110101100000011 ?
b101101101000110010011010110101010000000010111100110101100000011 <
b101101101000110010011010110101010000000010111100110101100000011 A
b101101101000110010011010110101010000000010111100110101100000011 C
b101 2"
b101 5"
b101 I
b101 L
b11 N
b11 Q
b10 S
b10 V
b1001 X
b1001 [
b1 ]
b1 `
b101 b
b101 e
b110 l
b110 o
b10 q
b10 t
b111 v
b111 y
b10 ""
b10 %"
b1100 '"
b1100 *"
b11 ,"
b11 /"
b1 1"
b1 4"
b1001111000010110001110010011010110101000110010010001101011000 :
b1001111000010110001110010011010110101000110010010001101011000 B
b101 3
b101 6"
b111001111000010110011010010011010110110000110010010001101011001 9
b111001111000010110011010010011010110110000110010010001101011001 ;
1#
#80000
b100000111010111101111100101100001010011000111100100010001000110 ,
b100000111010111101111100101100001010011000111100100010001000110 >
b100000111010111101111100101100001010011000111100100010001000110 @
b1000 E
b1000 H
b1011 J
b1011 M
b0 ^
b0 a
b1101 c
b1101 f
b101 w
b101 z
b100101101000110010001010110101010001101000011100110101110111000 ?
b100101101000110010001010110101010001101000011100110101110111000 <
b100101101000110010001010110101010001101000011100110101110111000 A
b100101101000110010001010110101010001101000011100110101110111000 C
b100 2"
b100 5"
b1011 D
b1011 G
b11 I
b11 L
b101 ]
b101 `
b111 b
b111 e
b1 v
b1 y
b1100 1"
b1100 4"
b1100001111000010110000010010011010110111010110010010001100111011 :
b1100001111000010110000010010011010110111010110010010001100111011 B
b1001 <"
b1000000000000000001011000000000000000011000000000000000001010101000000000001100 8"
b100 ;"
b10010000000000000001011000000000000000011000000000000000001010101000000000001100 :"
b1011000000000000000011000000000000000001010000000000000001100010 -
b1011000000000000000011000000000000000001010000000000000001100010 =
b1011000000000000000011000000000000000001010000000000000001100010 9"
0#
#84000
b1010 (
b1100000001101011101000100001010100101010000100111000100011101 ,
b1100000001101011101000100001010100101010000100111000100011101 >
b1100000001101011101000100001010100101010000100111000100011101 @
b1001 E
b1001 H
b110 J
b110 M
b1001 O
b1001 R
b1001 T
b1001 W
b1 Y
b1 \
b110 c
b110 f
b0 h
b0 k
b11 m
b11 p
b0 r
b0 u
b110 w
b110 z
b1000 |
b1000 !"
b1101 #"
b1101 &"
b111 ("
b111 +"
b101 -"
b101 0"
b10010101111101100001100000001100000110000000011001100101101001 ?
b10010101111101100001100000001100000110000000011001100101101001 <
b10010101111101100001100000001100000110000000011001100101101001 A
b10010101111101100001100000001100000110000000011001100101101001 C
b10 2"
b10 5"
b100 D
b100 G
b10 I
b10 L
b100 N
b100 Q
b100 S
b100 V
b1110 X
b1110 [
b10 b
b10 e
b101 g
b101 j
b1000 l
b1000 o
b101 q
b101 t
b10 v
b10 y
b1011 {
b1011 ~
b111 ""
b111 %"
b1101 '"
b1101 *"
b1 ,"
b1 /"
b1111 1"
b1111 4"
b1111000111010111101100100101100001010010010111100100010000100100 :
b1111000111010111101100100101100001010010010111100100010000100100 B
b110 3
b110 6"
b100000111010111101111100101100001010011000111100100010001000110 9
b100000111010111101111100101100001010011000111100100010001000110 ;
1#
#88000
b1100000101110111110000110000110101101011000101111110100011100 ,
b1100000101110111110000110000110101101011000101111110100011100 >
b1100000101110111110000110000110101101011000101111110100011100 @
b100 E
b100 H
b1010 J
b1010 M
b1110 ^
b1110 a
b11 w
b11 z
b1111 |
b1111 !"
b111010101111101111100110000001100000110111000011001100110100100 ?
b111010101111101111100110000001100000110111000011001100110100100 <
b111010101111101111100110000001100000110111000011001100110100100 A
b111010101111101111100110000001100000110111000011001100110100100 C
b111 2"
b111 5"
b1100 D
b1100 G
b110 I
b110 L
b1001 ]
b1001 `
b1000 v
b1000 y
b1010 {
b1010 ~
b1101 1"
b1101 4"
b1101000111010111101010000101100001010010100111100100010001101100 :
b1101000111010111101010000101100001010010100111100100010001101100 B
b0 <"
b1010000000000011001001000000000000000101100000000000000001100110000000000000101 8"
b101 ;"
b11001001000000000000000101100000000000000001100110000000000000101 :"
b1001000000000000000101100000000000000001100000000000000000101010 -
b1001000000000000000101100000000000000001100000000000000000101010 =
b1001000000000000000101100000000000000001100000000000000000101010 9"
0#
#92000
b1011 (
b1010000011001000011101010011100010100111111101110110100110 ,
b1010000011001000011101010011100010100111111101110110100110 >
b1010000011001000011101010011100010100111111101110110100110 @
b1010 E
b1010 H
b1011 J
b1011 M
b111 O
b111 R
b10 T
b10 W
b110 Y
b110 \
b1 ^
b1 a
b100 c
b100 f
b1111 h
b1111 k
b101 m
b101 p
b1010 r
b1010 u
b1 w
b1 z
b1 |
b1 !"
b1 #"
b1 &"
b110 ("
b110 +"
b11 -"
b11 0"
b11001101100001000100011010010111110100000101100010011110111010 ?
b11001101100001000100011010010111110100000101100010011110111010 <
b11001101100001000100011010010111110100000101100010011110111010 A
b11001101100001000100011010010111110100000101100010011110111010 C
b11 2"
b11 5"
b110 D
b110 G
b11 I
b11 L
b1101 N
b1101 Q
b1111 S
b1111 V
b10 X
b10 [
b1110 ]
b1110 `
b1100 b
b1100 e
b1010 g
b1010 j
b1 l
b1 o
b110 q
b110 t
b1110 v
b1110 y
b1110 {
b1110 ~
b1110 ""
b1110 %"
b10 '"
b10 *"
b1000 ,"
b1000 /"
b1000 1"
b1000 4"
b1000100000101110111011100110000110101100111000101111110100110110 :
b1000100000101110111011100110000110101100111000101111110100110110 B
b111 3
b111 6"
b1100000101110111110000110000110101101011000101111110100011100 9
b1100000101110111110000110000110101101011000101111110100011100 ;
1#
#96000
b111010100000101001011011011001111110111111111100010110100100 ,
b111010100000101001011011011001111110111111111100010110100100 >
b111010100000101001011011011001111110111111111100010110100100 @
b10 E
b10 H
b110 J
b110 M
b1111 ^
b1111 a
b10 c
b10 f
b1111 w
b1111 z
b1010 |
b1010 !"
b10 #"
b10 &"
b101001101100010101011111010010111110010111101100010011101100010 ?
b101001101100010101011111010010111110010111101100010011101100010 <
b101001101100010101011111010010111110010111101100010011101100010 A
b101001101100010101011111010010111110010111101100010011101100010 C
b101 2"
b101 5"
b1111 D
b1111 G
b10 I
b10 L
b1010 ]
b1010 `
b1111 b
b1111 e
b1010 v
b1010 y
b110 {
b110 ~
b1111 ""
b1111 %"
b1 1"
b1 4"
b1100000101111011010100110000110101111101000101111110100101111 :
b1100000101111011010100110000110101111101000101111110100101111 B
b1010 <"
b1100000000000001010000000000000001100100100000000000000010110111000000000000110 8"
b110 ;"
b10100000000000001010000000000000001100100100000000000000010110111000000000000110 :"
b1100100100000000000000010110000000000000000110011 -
b1100100100000000000000010110000000000000000110011 =
b1100100100000000000000010110000000000000000110011 9"
0#
